llama_index/storage/chat_store/dynamodb/__init__.py
llama_index/storage/chat_store/dynamodb/base.py
llama_index_storage_chat_store_dynamodb-0.4.2.dist-info/METADATA
llama_index_storage_chat_store_dynamodb-0.4.2.dist-info/WHEEL
llama_index_storage_chat_store_dynamodb-0.4.2.dist-info/licenses/LICENSE
llama_index_storage_chat_store_dynamodb-0.4.2.dist-info/RECORD
