Metadata-Version: 2.4
Name: llama-index-storage-chat-store-dynamodb
Version: 0.4.2
Summary: llama-index storage-chat-store aws dynamodb integration
Author-email: brycecf <26725654+brycecf@users.noreply.github.com>
License-Expression: MIT
License-File: LICENSE
Requires-Python: <4.0,>=3.9
Requires-Dist: aioboto3<16,>=13.1.1
Requires-Dist: boto3-stubs[dynamodb]<2,>=1.35.14
Requires-Dist: boto3<2,>=1.34.120
Requires-Dist: llama-index-core<0.15,>=0.13.0
